metabatch/__init__.py
metabatch/dataloader.py
metabatch/dataset.py
metabatch-0.9.1.dist-info/METADATA
metabatch-0.9.1.dist-info/WHEEL
metabatch-0.9.1.dist-info/licenses/LICENSE
metabatch-0.9.1.dist-info/RECORD
