Metadata-Version: 2.3
Name: metabatch
Version: 0.9.1
Summary: MetaBatch: A micro-framework for efficient batching of tasks in PyTorch.
Project-URL: Homepage, https://github.com/DubiousCactus/metabatch
Project-URL: Bug Tracker, https://github.com/DubiousCactus/metabatch/issues
Author-email: Théo Morales <moralest@tcd.ie>
License-File: LICENSE
Keywords: MAML,dataset,deep,few-shot,learning,meta,meta-learning,pytorch,task,taskset
Classifier: Development Status :: 4 - Beta
Classifier: Intended Audience :: Developers
Classifier: License :: OSI Approved :: MIT License
Classifier: Operating System :: OS Independent
Classifier: Programming Language :: Python :: 3
Classifier: Topic :: Scientific/Engineering :: Artificial Intelligence
Requires-Python: >=3.7
